BeyotekTools/__init__.py
BeyotekTools/awsutil.py
BeyotekTools/mongodbproductutil.py
BeyotekTools/mongodbproxyutil.py
BeyotekTools/networkutil.py
BeyotekTools/scraperutil.py
BeyotekTools/speedlimit.py
BeyotekTools/stringutil.py
BeyotekTools/test.py
BeyotekTools-0.0.46.dist-info/LICENSE
BeyotekTools-0.0.46.dist-info/METADATA
BeyotekTools-0.0.46.dist-info/WHEEL
BeyotekTools-0.0.46.dist-info/top_level.txt
BeyotekTools-0.0.46.dist-info/RECORD
