Metadata-Version: 2.1
Name: BeyotekTools
Version: 0.0.46
Summary: Beyotek Tools
Author-email: Beyotek Inc <chuck@beyotek.com>
Classifier: Programming Language :: Python :: 3
Classifier: License :: OSI Approved :: MIT License
Classifier: Operating System :: OS Independent
Requires-Python: >=3.7
License-File: LICENSE
